LICENSE
README.md
setup.py
src/surepylib/__init__.py
src/surepylib/btcfun.py
src/surepylib/ethfun.py
src/surepylib/pubfun.py
src/surepylib/test.py
src/surepylib.egg-info/PKG-INFO
src/surepylib.egg-info/SOURCES.txt
src/surepylib.egg-info/dependency_links.txt
src/surepylib.egg-info/top_level.txt