Metadata-Version: 2.1
Name: surepylib
Version: 1.1.0
Summary: surepylib
Author: surepylib
Author-email: sure@surepylib.com
Requires-Python: >=3.6
License-File: LICENSE
